MANIFEST.in
requirements.txt
setup.py
stock/__init__.py
stock/__main__.py
stock/charts.py
stock/config.py
stock/jupyter.py
stock/models.py
stock/query.py
stock/signals.py
stock/simulate.py
stock/util.py
stock.egg-info/PKG-INFO
stock.egg-info/SOURCES.txt
stock.egg-info/dependency_links.txt
stock.egg-info/entry_points.txt
stock.egg-info/requires.txt
stock.egg-info/top_level.txt
stock/cli/__init__.py
stock/cli/calc.py
stock/cli/config.py
stock/cli/db.py
stock/cli/import_company.py
stock/cli/main.py
stock/cli/predict.py
stock/cli/quandl.py
stock/cli/query.py
stock/cli/scrape.py
stock/cli/server.py
stock/cli/simulate.py
stock/scrape/yahoo_japan.py