Metadata-Version: 1.0
Name: stock
Version: 2.0
Summary: A command line tool for stock markets
Home-page: http://f1nance.herokuapp.com/
Author: Hiroyuki Ishii
Author-email: hiroyuki.ishii.42@gmail.com
License: UNKNOWN
Keywords: stock
Platform: UNKNOWN
